README.md
setup.py
FeatureMapVisualizer/__init__.py
FeatureMapVisualizer/save_features.py
FeatureMapVisualizer/visualizer.py
FeatureMapVisualizer.egg-info/PKG-INFO
FeatureMapVisualizer.egg-info/SOURCES.txt
FeatureMapVisualizer.egg-info/dependency_links.txt
FeatureMapVisualizer.egg-info/requires.txt
FeatureMapVisualizer.egg-info/top_level.txt