Metadata-Version: 2.1
Name: FeatureMapVisualizer
Version: 1.0.3
Summary: CNN Feature Map Visualizations
Home-page: https://github.com/lukysummer/FeatureMapVisualizer
Author: Jahyun Shin
Author-email: lucrece.shin@mail.utorotno.ca
License: MIT
Download-URL: https://github.com/lukysummer/FeatureMapVisualizer/archive/refs/tags/v1.0.3.tar.gz
Keywords: artificial intelligence,machine learning,visualization,image recognition,computer vision,CNN
Platform: UNKNOWN
Classifier: Development Status :: 3 - Alpha
Classifier: Intended Audience :: Developers
Classifier: Topic :: Software Development :: Build Tools
Classifier: License :: OSI Approved :: MIT License
Classifier: Programming Language :: Python :: 3
Classifier: Programming Language :: Python :: 3.6
Classifier: Programming Language :: Python :: 3.7
Classifier: Programming Language :: Python :: 3.8
Classifier: Topic :: Scientific/Engineering :: Artificial Intelligence
